[
  {
    "id": 1,
    "name": "Jonrad",
    "surname": "Kopek",
    "email": "kopekj@email.com"
  },
  {
    "id": 2,
    "name": "Patryk",
    "surname": "Mendelewski",
    "email": "jestem@simpem.com"
  },
  {
    "id": 3,
    "name": "Przypadkowe",
    "surname": "Imie",
    "email": "eeeee@bbbb.com"
  },
  {
    "id": 4,
    "name": "John",
    "surname": "Doe",
    "email": "john.doe@example.com"
  },
  {
    "id": 5,
    "name": "Jane",
    "surname": "Smith",
    "email": "jane.smith@example.com"
  },
  {
    "id": 6,
    "name": "Bob",
    "surname": "Johnson",
    "email": "bob.johnson@example.com"
  },
  {
    "id": 7,
    "name": "Alice",
    "surname": "Williams",
    "email": "alice.williams@example.com"
  },
  {
    "id": 8,
    "name": "Charlie",
    "surname": "Brown",
    "email": "charlie.brown@example.com"
  },
  {
    "id": 9,
    "name": "Eve",
    "surname": "Davis",
    "email": "eve.davis@example.com"
  },
  {
    "id": 10,
    "name": "David",
    "surname": "Lee",
    "email": "david.lee@example.com"
  }
]